zmk/__init__.py
zmk/_version.py
zmk/backports.py
zmk/build.py
zmk/config.py
zmk/exceptions.py
zmk/hardware.py
zmk/main.py
zmk/menu.py
zmk/prompt.py
zmk/remote.py
zmk/repo.py
zmk/shell.py
zmk/styles.py
zmk/terminal.py
zmk/util.py
zmk/yaml.py
zmk/commands/__init__.py
zmk/commands/cd.py
zmk/commands/code.py
zmk/commands/config.py
zmk/commands/download.py
zmk/commands/init.py
zmk/commands/version.py
zmk/commands/west.py
zmk/commands/keyboard/__init__.py
zmk/commands/keyboard/add.py
zmk/commands/keyboard/list.py
zmk/commands/keyboard/new.py
zmk/commands/keyboard/remove.py
zmk/commands/module/__init__.py
zmk/commands/module/add.py
zmk/commands/module/list.py
zmk/commands/module/remove.py
zmk/templates/__init__.py
zmk/templates/board/nrf52840/Kconfig
zmk/templates/board/nrf52840/Kconfig.defconfig
zmk/templates/board/nrf52840/board.cmake
zmk/templates/board/nrf52840/board.yaml
zmk/templates/board/nrf52840/board_defconfig
zmk/templates/board/nrf52840/common_inner.dtsi
zmk/templates/board/nrf52840/common_outer.dtsi
zmk/templates/board/nrf52840/pinctrl.dtsi
zmk/templates/board/nrf52840/split/${id}-layouts.dtsi
zmk/templates/board/nrf52840/split/${id}.conf
zmk/templates/board/nrf52840/split/${id}.dtsi
zmk/templates/board/nrf52840/split/${id}.keymap
zmk/templates/board/nrf52840/split/${id}.yaml
zmk/templates/board/nrf52840/split/${id}.zmk.yml
zmk/templates/board/nrf52840/split/${id}_left-pinctrl.dtsi
zmk/templates/board/nrf52840/split/${id}_left.dts
zmk/templates/board/nrf52840/split/${id}_left_defconfig
zmk/templates/board/nrf52840/split/${id}_right-pinctrl.dtsi
zmk/templates/board/nrf52840/split/${id}_right.dts
zmk/templates/board/nrf52840/split/${id}_right_defconfig
zmk/templates/board/nrf52840/split/Kconfig
zmk/templates/board/nrf52840/split/Kconfig.${id}_left
zmk/templates/board/nrf52840/split/Kconfig.${id}_right
zmk/templates/board/nrf52840/split/Kconfig.defconfig
zmk/templates/board/nrf52840/split/board.cmake
zmk/templates/board/nrf52840/split/board.yml
zmk-0.4.0.dist-info/licenses/LICENSE
zmk-0.4.0.dist-info/METADATA
zmk-0.4.0.dist-info/WHEEL
zmk-0.4.0.dist-info/entry_points.txt
zmk-0.4.0.dist-info/top_level.txt
zmk-0.4.0.dist-info/RECORD
