Metadata-Version: 2.4
Name: zmk
Version: 0.4.0
Summary: A command line program to help set up ZMK Firmware
License: MIT License
Project-URL: Chat, https://zmk.dev/community/discord/invite
Project-URL: Documentation, https://zmk.dev/docs
Project-URL: Issue Tracker, https://github.com/zmkfirmware/zmk-cli/issues/
Project-URL: Source Code, https://github.com/zmkfirmware/zmk-cli/
Classifier: Development Status :: 3 - Alpha
Classifier: Environment :: Console
Classifier: Intended Audience :: Developers
Classifier: Intended Audience :: End Users/Desktop
Classifier: License :: OSI Approved :: MIT License
Classifier: Operating System :: OS Independent
Classifier: Topic :: Software Development
Classifier: Topic :: Utilities
Requires-Python: >=3.10
License-File: LICENSE
Requires-Dist: backports.strenum; python_version < "3.11"
Requires-Dist: dacite<2.0.0,>=1.9.2
Requires-Dist: giturlparse<0.15.0,>=0.14.0
Requires-Dist: mako<2.0.0,>=1.3.10
Requires-Dist: rich<15.0.0,>=14.2.0
Requires-Dist: ruamel.yaml<0.19.0,>=0.18.17
Requires-Dist: shellingham<2.0.0,>=1.5.4
Requires-Dist: typer<0.22.0,>=0.21.0
Requires-Dist: west<2.0.0,>=1.5.0
Provides-Extra: dev
Requires-Dist: pre-commit; extra == "dev"
Requires-Dist: pylint; extra == "dev"
Requires-Dist: pyright; extra == "dev"
Dynamic: license-file
